flake8_no_private_methods/__init__.py
flake8_no_private_methods/plugin.py
flake8_no_private_methods/py.typed
flake8_no_private_methods-0.0.1.dist-info/LICENSE
flake8_no_private_methods-0.0.1.dist-info/METADATA
flake8_no_private_methods-0.0.1.dist-info/WHEEL
flake8_no_private_methods-0.0.1.dist-info/entry_points.txt
flake8_no_private_methods-0.0.1.dist-info/RECORD
