Metadata-Version: 2.1
Name: flake8-no-private-methods
Version: 0.0.1
Summary: This is how python package should look like!
Home-page: https://github.com/blablatdinov/flake8-no-private-methods
License: MIT
Requires-Python: >=3.9,<4.0
Classifier: Development Status :: 3 - Alpha
Classifier: Intended Audience :: Developers
Classifier: License :: OSI Approved :: MIT License
Classifier: Operating System :: OS Independent
Classifier: Programming Language :: Python :: 3
Classifier: Programming Language :: Python :: 3.9
Classifier: Programming Language :: Python :: 3.10
Classifier: Programming Language :: Python :: 3.11
Classifier: Programming Language :: Python :: 3.12
Classifier: Programming Language :: Python :: 3.13
Classifier: Topic :: Software Development :: Libraries :: Python Modules
Requires-Dist: flake8 (>=5.0.0)
Project-URL: Repository, https://github.com/blablatdinov/flake8-no-private-methods
